LICENSE.rst
MANIFEST.in
README.rst
setup.cfg
setup.py
versioneer.py
progress_reporter/__init__.py
progress_reporter/_version.py
progress_reporter/notebook.py
progress_reporter/reporter.py
progress_reporter.egg-info/PKG-INFO
progress_reporter.egg-info/SOURCES.txt
progress_reporter.egg-info/dependency_links.txt
progress_reporter.egg-info/top_level.txt
progress_reporter/_vendor/__init__.py
progress_reporter/_vendor/tqdm/__init__.py
progress_reporter/_vendor/tqdm/__main__.py
progress_reporter/_vendor/tqdm/_main.py
progress_reporter/_vendor/tqdm/_monitor.py
progress_reporter/_vendor/tqdm/_tqdm.py
progress_reporter/_vendor/tqdm/_tqdm_gui.py
progress_reporter/_vendor/tqdm/_tqdm_notebook.py
progress_reporter/_vendor/tqdm/_tqdm_pandas.py
progress_reporter/_vendor/tqdm/_utils.py
progress_reporter/_vendor/tqdm/_version.py
progress_reporter/_vendor/tqdm/auto/__init__.py
progress_reporter/_vendor/tqdm/autonotebook/__init__.py
tests/test_progress.py