Metadata-Version: 1.1
Name: progress-reporter
Version: 2.0
Summary: UNKNOWN
Home-page: https://github.com/marscher/progress_reporter
Author: UNKNOWN
Author-email: UNKNOWN
License: MIT
Keywords: progress,reporting,eta,gui
Platform: UNKNOWN
Classifier: Development Status :: 5 - Production/Stable
Classifier: Environment :: Console
Classifier: Environment :: Web Environment
Classifier: Intended Audience :: Developers
Classifier: License :: OSI Approved :: MIT License
Classifier: Natural Language :: English
Classifier: Operating System :: POSIX
Classifier: Operating System :: Microsoft :: Windows
Classifier: Programming Language :: Python :: 2.7
Classifier: Programming Language :: Python :: 3
Classifier: Topic :: Software Development :: User Interfaces
Classifier: Topic :: Software Development :: Widget Sets
Classifier: Topic :: Utilities
